generate_wiki/__init__.py
generate_wiki/generate_wiki.py
generate_wiki-1.0.1.dist-info/METADATA
generate_wiki-1.0.1.dist-info/RECORD
generate_wiki-1.0.1.dist-info/WHEEL
generate_wiki-1.0.1.dist-info/entry_points.txt
generate_wiki-1.0.1.dist-info/top_level.txt
