Metadata-Version: 2.1
Name: generate-wiki
Version: 1.0.1
Summary: A wiki generation package for the Sample Programs repo
Home-page: https://github.com/TheRenegadeCoder/sample-programs-wiki-generator
Author: The Renegade Coder
Author-email: jeremy.grifski@therenegadecoder.com
License: UNKNOWN
Platform: UNKNOWN
Classifier: Programming Language :: Python :: 3
Classifier: License :: OSI Approved :: GNU General Public License v3 (GPLv3)
Classifier: Operating System :: OS Independent
